django_evostream-0.1b2.dist-info/DESCRIPTION.rst
django_evostream-0.1b2.dist-info/METADATA
django_evostream-0.1b2.dist-info/RECORD
django_evostream-0.1b2.dist-info/WHEEL
django_evostream-0.1b2.dist-info/metadata.json
django_evostream-0.1b2.dist-info/top_level.txt
evostream/__init__.py
evostream/commands.py
evostream/default.py
evostream/protocols.py
evostream/utils.py
evostream/conf/__init__.py
evostream/conf/defaults.py
evostream/management/__init__.py
evostream/management/base.py
evostream/management/commands/__init__.py
evostream/management/commands/listconfig.py
evostream/management/commands/liststreams.py
tests/__init__.py
